oitei/__init__.py
oitei/converter.py
oitei/namespaces.py
oitei/tei_template.py
oitei-1.1.1.dist-info/METADATA
oitei-1.1.1.dist-info/WHEEL
oitei-1.1.1.dist-info/top_level.txt
oitei-1.1.1.dist-info/RECORD
