Metadata-Version: 2.1
Name: oitei
Version: 1.1.1
Summary: OpenITI mARkdown to TEI converter
Home-page: http://github.com/OpenITI/oitei
Author: Raff Viglianti
Author-email: rviglian@umd.edu
License: UNKNOWN
Platform: UNKNOWN
Requires-Python: >=3.8
Requires-Dist: lxml
Requires-Dist: oimdp
